{"name":"Buscar un producto","id":"probar-la-busqueda-de-productos-en-el-home-de-zippo;buscar-un-producto","testSteps":[{"number":1,"description":"Dado estoy en la pagina Home de Zippo","duration":20017,"startTime":"2022-08-05T18:43:31.067-05:00[America/Bogota]","result":"SUCCESS","precondition":false,"level":0},{"number":2,"description":"Cuando escribo el termino en la caja de busqueda y le doy enter","duration":23255,"startTime":"2022-08-05T18:43:51.087-05:00[America/Bogota]","result":"SUCCESS","precondition":false,"level":0},{"number":3,"description":"Entonces obtengo productos de Zippo relacionados con la busqueda","duration":581,"startTime":"2022-08-05T18:44:14.343-05:00[America/Bogota]","result":"SUCCESS","precondition":false,"level":0}],"userStory":{"id":"probar-la-busqueda-de-productos-en-el-home-de-zippo","storyName":"Probar la busqueda de productos en el Home de Zippo","path":"src/test/resources/co/com/zippo/www/features/buscarHome.feature","type":"feature"},"featureTag":{"name":"Features/Probar la busqueda de productos en el Home de Zippo","type":"feature","displayName":"Features/Probar la busqueda de productos en el Home de Zippo"},"title":"Buscar un producto","startTime":"2022-08-05T18:43:31.016-05:00[America/Bogota]","duration":43909,"projectKey":"","isManualTestingUpToDate":false,"manual":false,"testSource":"Cucumber","result":"SUCCESS"}